MANIFEST.in
README.md
setup.cfg
setup.py
trex_web.egg-info/PKG-INFO
trex_web.egg-info/SOURCES.txt
trex_web.egg-info/dependency_links.txt
trex_web.egg-info/entry_points.txt
trex_web.egg-info/not-zip-safe
trex_web.egg-info/requires.txt
trex_web.egg-info/top_level.txt
trexweb/__init__.py
trexweb/__main__.py
trexweb/conf.py
trexweb/controllers/__init__.py
trexweb/controllers/demo/__init__.py
trexweb/controllers/demo/merchant_demo_tour_routes.py
trexweb/controllers/main/__init__.py
trexweb/controllers/main/blogs_routes.py
trexweb/controllers/main/contact_to_us_routes.py
trexweb/controllers/main/custom_routes.py
trexweb/controllers/main/demo_request_routes.py
trexweb/controllers/main/join_as_partner_routes.py
trexweb/controllers/main/main_routes.py
trexweb/controllers/main/marketing_routes.py
trexweb/controllers/main/memberasia_app_routes.py
trexweb/controllers/main/product_routes.py
trexweb/controllers/merchant/__init__.py
trexweb/controllers/merchant/merchant_customization_routes.py
trexweb/controllers/presentation/__init__.py
trexweb/controllers/presentation/presentation_routes.py
trexweb/controllers/recruit/__init__.py
trexweb/controllers/recruit/recruit_routes.py
trexweb/controllers/security/__init__.py
trexweb/controllers/security/security_routes.py
trexweb/controllers/system/__init__.py
trexweb/controllers/system/custom_routes.py
trexweb/controllers/system/mailjet_service_routes.py
trexweb/controllers/system/system_routes.py
trexweb/controllers/system/system_static_routes.py
trexweb/controllers/system/web_beacon_email_tracking_routes.py
trexweb/controllers/system/data/__init__.py
trexweb/forms/__init__.py
trexweb/forms/admin_forms.py
trexweb/forms/base_forms.py
trexweb/forms/recruit_forms.py
trexweb/forms/system_forms.py
trexweb/forms/user_forms.py
trexweb/libs/__init__.py
trexweb/libs/decorators.py
trexweb/libs/http.py
trexweb/libs/oauth_signin.py
trexweb/libs/flask/__init__.py
trexweb/libs/flask/exceptions.py
trexweb/libs/flask/middleware.py
trexweb/libs/flask/pagination.py
trexweb/libs/flask/decorator/__init__.py
trexweb/libs/flask/decorator/common_decorators.py
trexweb/libs/flask/decorator/security_decorators.py
trexweb/libs/flask/middleware/__init__.py
