Metadata-Version: 2.4
Name: trex-web
Version: 1.0.4
Summary: TRex web package
Author: Jack Lok
Requires-Dist: flask
Requires-Dist: Jinja2
Requires-Dist: MarkupSafe
Requires-Dist: phonenumbers
Requires-Dist: requests
Requires-Dist: testfixtures
Requires-Dist: flask-babel
Requires-Dist: Flask-CORS
Dynamic: author
Dynamic: requires-dist
Dynamic: summary
